team8/sound_counter/counter.v
// 사운드 길이 카운터
module counter_sound(
    input clk,
    input en,
    output wire sound
    );
    
    reg [2:0] count;

    always @ (posedge clk or posedge en) 
    begin
      
      if(en == 1)
        count <= count + 1;

      else
        count <= 3'b000;
    
    end

    assign sound = (count == 3'b111 ) ? 0 : 1;

endmodule

team8/sound_counter/sound.v
module shock_sound(
    input wire clk,
    input wire shock,
    input wire rst,
    output reg sound
);


    counter_sound count (
    .clk(clk),
    .en(en),
    .sound(sound_end)
    );

reg en;
wire sound_end;

always @(negedge shock) begin
    en <= 1;    
end

always @(posedge clk or rst) begin
    if (rst!=1) begin
        if (shock == 1) begin
            sound <= 1;
            en <= 0;
        end
        else
            sound <= sound_end & sound;
    end

    else 
        sound <= 0;

end

endmodule

team8/sound_counter/tb_sound.v
module tb_sound;

    reg clk;
    reg shock;
    reg rst;
    wire sound;

    shock_sound uut (
        .clk(clk),
        .shock(shock),
        .rst(rst),
        .sound(sound)
    );

initial
   begin
      $dumpfile("test_out.vcd");
      $dumpvars(0,tb_sound);  // tb는 위에 nand4_if tb(a,y)의 tb를 말한다. 
      $display("good");
   end

    always #1 clk = ~clk;

initial begin
        clk = 0;
        shock = 0;
        rst = 1;

        #4 rst = 0;
        #4 shock = 1;
        #4 shock = 0;
        #4 shock = 1;
        #4 shock = 0;
        #40 $finish;
end

endmodule

team8/sound_counter/test_out.vcd
$date
	Tue Dec 14 08:05:33 2021
$end
$version
	Icarus Verilog
$end
$timescale
	1s
$end
$scope module tb_sound $end
$var wire 1 ! sound $end
$var reg 1 " clk $end
$var reg 1 # rst $end
$var reg 1 $ shock $end
$scope module uut $end
$var wire 1 " clk $end
$var wire 1 # rst $end
$var wire 1 $ shock $end
$var wire 1 % sound_end $end
$var reg 1 & en $end
$var reg 1 ! sound $end
$scope module count $end
$var wire 1 " clk $end
$var wire 1 & en $end
$var wire 1 % sound $end
$var reg 3 ' count [2:0] $end
$upscope $end
$upscope $end
$upscope $end
$enddefinitions $end
#0
$dumpvars
bx '
1&
x%
0$
1#
0"
0!
$end
#1
1"
#2
0"
#3
1"
#4
0"
0#
#5
1"
#6
0"
#7
1"
#8
0"
1$
#9
0&
1!
1"
#10
0"
#11
1%
b0 '
1"
#12
b1 '
1&
0"
0$
#13
b10 '
1"
#14
0"
#15
b11 '
1"
#16
0"
1$
#17
b100 '
0&
1"
#18
0"
#19
b0 '
1"
#20
b1 '
1&
0"
0$
#21
b10 '
1"
#22
0"
#23
b11 '
1"
#24
0"
#25
b100 '
1"
#26
0"
#27
b101 '
1"
#28
0"
#29
b110 '
1"
#30
0"
#31
0%
b111 '
1"
#32
0"
#33
1%
b0 '
0!
1"
#34
0"
#35
b1 '
1"
#36
0"
#37
b10 '
1"
#38
0"
#39
b11 '
1"
#40
0"
#41
b100 '
1"
#42
0"
#43
b101 '
1"
#44
0"
#45
b110 '
1"
#46
0"
#47
0%
b111 '
1"
#48
0"
#49
1%
b0 '
1"
#50
0"
#51
b1 '
1"
#52
0"
#53
b10 '
1"
#54
0"
#55
b11 '
1"
#56
0"
#57
b100 '
1"
#58
0"
#59
b101 '
1"
